mongoengine_bundle/__init__.py
mongoengine_bundle/bundle.py
mongoengine_bundle-1.5.dist-info/LICENSE
mongoengine_bundle-1.5.dist-info/METADATA
mongoengine_bundle-1.5.dist-info/WHEEL
mongoengine_bundle-1.5.dist-info/top_level.txt
mongoengine_bundle-1.5.dist-info/RECORD
