Metadata-Version: 2.1
Name: mongoengine-bundle
Version: 1.5
Summary: mongoengine support for applauncher
Home-page: https://github.com/applauncher-team/mongoengine_bundle
Author: Alvaro Garcia Gomez
Author-email: maxpowel@gmail.com
License: UNKNOWN
Download-URL: https://github.com/applauncher-team/mongoengine_bundle/archive/master.zip
Keywords: mongoengine,applauncher
Platform: UNKNOWN
Classifier: Topic :: Adaptive Technologies
Classifier: Topic :: Software Development
Classifier: Topic :: System
Classifier: Topic :: Utilities
Requires-Dist: applauncher
Requires-Dist: mongoengine
